_maix.cpython-39-aarch64-linux-gnu.so
_maix_camera.cpython-39-aarch64-linux-gnu.so
_maix_display.cpython-39-aarch64-linux-gnu.so
_maix_image.cpython-39-aarch64-linux-gnu.so
_maix_nn.cpython-39-aarch64-linux-gnu.so
_maix_nn_decoder_retinaface.cpython-39-aarch64-linux-gnu.so
_maix_speech.cpython-39-aarch64-linux-gnu.so
pylibi2c.cpython-39-aarch64-linux-gnu.so
maix/__init__.py
maix/camera.py
maix/display.py
maix/event.py
maix/gpio.py
maix/i2c.py
maix/image.py
maix/libaipudrv.so
maix/libaipudrv.so.4
maix/libasound.so
maix/libjpeg.so.9
maix/libmaix_cam.so
maix/libmaix_disp.so
maix/libmaix_image.so
maix/libmaix_nn.so
maix/libmaix_nn_app.so
maix/libmaix_nn_decoder.so
maix/libmaix_utils.so
maix/libopencv_alphamat.so
maix/libopencv_aruco.so
maix/libopencv_bgsegm.so
maix/libopencv_bioinspired.so
maix/libopencv_calib3d.so
maix/libopencv_ccalib.so
maix/libopencv_core.so
maix/libopencv_datasets.so
maix/libopencv_dnn.so
maix/libopencv_dnn_objdetect.so
maix/libopencv_dnn_superres.so
maix/libopencv_dpm.so
maix/libopencv_face.so
maix/libopencv_features2d.so
maix/libopencv_flann.so
maix/libopencv_freetype.so
maix/libopencv_fuzzy.so
maix/libopencv_hdf.so
maix/libopencv_hfs.so
maix/libopencv_highgui.so
maix/libopencv_img_hash.so
maix/libopencv_imgcodecs.so
maix/libopencv_imgproc.so
maix/libopencv_intensity_transform.so
maix/libopencv_line_descriptor.so
maix/libopencv_mcc.so
maix/libopencv_ml.so
maix/libopencv_objdetect.so
maix/libopencv_optflow.so
maix/libopencv_phase_unwrapping.so
maix/libopencv_photo.so
maix/libopencv_plot.so
maix/libopencv_quality.so
maix/libopencv_rapid.so
maix/libopencv_reg.so
maix/libopencv_rgbd.so
maix/libopencv_saliency.so
maix/libopencv_shape.so
maix/libopencv_stereo.so
maix/libopencv_stitching.so
maix/libopencv_structured_light.so
maix/libopencv_superres.so
maix/libopencv_surface_matching.so
maix/libopencv_text.so
maix/libopencv_tracking.so
maix/libopencv_video.so
maix/libopencv_videoio.so
maix/libopencv_videostab.so
maix/libopencv_viz.so
maixpy3-0.5.3.dist-info/LICENSE
maixpy3-0.5.3.dist-info/METADATA
maixpy3-0.5.3.dist-info/WHEEL
maixpy3-0.5.3.dist-info/entry_points.txt
maixpy3-0.5.3.dist-info/top_level.txt
maixpy3-0.5.3.dist-info/RECORD
