Metadata-Version: 2.1
Name: maixpy3
Version: 0.5.3
Summary: MaixPy Python3 library
Home-page: https://github.com/sipeed/maixpy3
Author: Sipeed
Author-email: support@sipeed.com
License: MIT
Platform: UNKNOWN
Classifier: Programming Language :: Python :: 3
Requires-Dist: numpy
Requires-Dist: rpyc
Requires-Dist: gpiod
Requires-Dist: evdev
Requires-Dist: spidev
Requires-Dist: pyserial
Provides-Extra: test
Requires-Dist: pytest ; extra == 'test'
